[
  {
    "timestamp": "2026-04-07T01:32:01.377308+00:00",
    "user": "User",
    "schemaType": "pathologist-source",
    "entityKey": "_study",
    "action": "create",
    "changes": {
      "pathologist_name": {
        "old": null,
        "new": "Smith J"
      },
      "grading_scale": {
        "old": null,
        "new": "5pt"
      },
      "cro_name": {
        "old": null,
        "new": "Acme Pathology"
      }
    }
  },
  {
    "timestamp": "2026-04-07T01:32:11.825918+00:00",
    "user": "User",
    "schemaType": "pathologist-source",
    "entityKey": "_study",
    "action": "create",
    "changes": {
      "pathologist_name": {
        "old": null,
        "new": "Smith J"
      },
      "grading_scale": {
        "old": null,
        "new": "5pt"
      },
      "cro_name": {
        "old": null,
        "new": "Acme Pathology"
      }
    }
  },
  {
    "timestamp": "2026-04-07T02:03:22.539360+00:00",
    "user": "User",
    "schemaType": "pathologist-source",
    "entityKey": "_study",
    "action": "create",
    "changes": {
      "pathologist_name": {
        "old": null,
        "new": "Smith J"
      },
      "cro_name": {
        "old": null,
        "new": "Acme Pathology"
      },
      "grading_scale": {
        "old": null,
        "new": "5pt"
      }
    }
  },
  {
    "timestamp": "2026-04-07T14:10:33.328282+00:00",
    "user": "User",
    "schemaType": "pathologist-source",
    "entityKey": "_study",
    "action": "create",
    "changes": {
      "grading_scale": {
        "old": null,
        "new": "5pt"
      },
      "cro_name": {
        "old": null,
        "new": "Acme Pathology"
      },
      "pathologist_name": {
        "old": null,
        "new": "Smith J"
      }
    }
  },
  {
    "timestamp": "2026-04-07T15:03:54.163935+00:00",
    "user": "User",
    "schemaType": "pathologist-source",
    "entityKey": "_study",
    "action": "create",
    "changes": {
      "cro_name": {
        "old": null,
        "new": "Acme Pathology"
      },
      "grading_scale": {
        "old": null,
        "new": "5pt"
      },
      "pathologist_name": {
        "old": null,
        "new": "Smith J"
      }
    }
  }
]